LICENSE.txt
MANIFEST.in
README.md
setup.py
energy_callback/__init__.py
energy_callback/callback.py
energy_callback/raplMonitor.py
energy_callback/tb_experiment_1.csv
energy_callback/test.py
energy_callback.egg-info/PKG-INFO
energy_callback.egg-info/SOURCES.txt
energy_callback.egg-info/dependency_links.txt
energy_callback.egg-info/requires.txt
energy_callback.egg-info/top_level.txt