Metadata-Version: 2.1
Name: energy-callback
Version: 0.1.12
License-File: LICENSE.txt
